lm_sdk/__init__.py
lm_sdk/api/LMChainService.py
lm_sdk/api/LMRequest.py
lm_sdk/api/__init__.py
lm_sdk/common/LMRsa.py
lm_sdk/common/LMServiceError.py
lm_sdk/common/LMTypeDTO.py
lm_sdk/common/__init__.py
milian_blockchain_sdk-1.0.1.dist-info/LICENSE
milian_blockchain_sdk-1.0.1.dist-info/METADATA
milian_blockchain_sdk-1.0.1.dist-info/WHEEL
milian_blockchain_sdk-1.0.1.dist-info/top_level.txt
milian_blockchain_sdk-1.0.1.dist-info/RECORD
