Metadata-Version: 2.1
Name: milian-blockchain-sdk
Version: 1.0.1
Summary: 链盟 Python SDK
Home-page: UNKNOWN
Author: 杭州米链科技有限公司
Author-email: hzqixunda@163.com
License: UNKNOWN
Platform: UNKNOWN
Classifier: Programming Language :: Python :: 3
Classifier: License :: OSI Approved :: MIT License
Classifier: Operating System :: OS Independent
Requires-Python: >=3.7
Requires-Dist: requests
Requires-Dist: pycryptodome
Requires-Dist: eth-account
Requires-Dist: eth-utils
